avotes_parser/core/ABI/__init__.py
avotes_parser/core/ABI/provider.py
avotes_parser/core/ABI/storage.py
avotes_parser/core/ABI/utilities/__init__.py
avotes_parser/core/ABI/utilities/etherscan.py
avotes_parser/core/ABI/utilities/exceptions.py
avotes_parser/core/ABI/utilities/local.py
avotes_parser/core/ABI/utilities/processing.py
avotes_parser/core/__init__.py
avotes_parser/core/decoding.py
avotes_parser/core/package.py
avotes_parser/core/parsing.py
avotes_parser/core/pretty_printed.py
avotes_parser/core/spec.py
avotes_parser_core-0.5.6.dist-info/METADATA
avotes_parser_core-0.5.6.dist-info/WHEEL
avotes_parser_core-0.5.6.dist-info/RECORD
