Metadata-Version: 2.1
Name: avotes-parser-core
Version: 0.5.6
Summary: Aragon votings parser library
License: MIT
Author: Dmitri Ivakhnenko
Author-email: dmit.ivh@gmail.com
Requires-Python: >=3.10,<4
Classifier: License :: OSI Approved :: MIT License
Classifier: Programming Language :: Python :: 3
Classifier: Programming Language :: Python :: 3.10
Classifier: Programming Language :: Python :: 3.11
Classifier: Programming Language :: Python :: 3.12
Requires-Dist: eth-brownie (>=1.20.0,<1.21.0)
Requires-Dist: requests (>=2.31.0,<2.32.0)
Requires-Dist: safe-pysha3 (>=1.0.4,<1.1.0)
Requires-Dist: setuptools (>=69.0.3,<69.1.0)
Requires-Dist: web3 (>=6.15.0,<6.16.0)
